ovos_ww_plugin_precise/__init__.py
ovos_ww_plugin_precise/version.py
ovos_ww_plugin_precise-0.1.1.dist-info/LICENSE
ovos_ww_plugin_precise-0.1.1.dist-info/METADATA
ovos_ww_plugin_precise-0.1.1.dist-info/WHEEL
ovos_ww_plugin_precise-0.1.1.dist-info/entry_points.txt
ovos_ww_plugin_precise-0.1.1.dist-info/top_level.txt
ovos_ww_plugin_precise-0.1.1.dist-info/zip-safe
ovos_ww_plugin_precise-0.1.1.dist-info/RECORD
